venvarium/__init__.py
venvarium/exceptions.py
venvarium/venvironment.py
venvarium-0.1.0.post1.dist-info/WHEEL
venvarium-0.1.0.post1.dist-info/METADATA
venvarium-0.1.0.post1.dist-info/RECORD
